Metadata-Version: 1.1
Name: lcalc
Version: 1.0
Summary: Lambda Calculus implementation
Home-page: https://github.com/dair-targ/lcalc
Author: Vladimir Berkutov
Author-email: vladimir.berkutov@gmail.com
License: GPLv3
Download-URL: https://github.com/dair-targ/lcalc/tarball/1.0
Platform: UNKNOWN
